{
  "@type" : "TEMPLATE",
  "uid" : "bf470ecd-6dcf-4307-8ac8-88ee85019905",
  "description" : {
    "@type" : "RESOURCE_DESCRIPTION",
    "originalAuthor" : {
      "date" : "2022-10-19"
    },
    "otherContributors" : [ ],
    "lifecycleState" : {
      "codeString" : "unmanaged"
    },
    "ipAcknowledgements" : { },
    "references" : { },
    "conversionDetails" : { },
    "otherDetails" : {
      "licence" : "This work is licensed under the Creative Commons Attribution-ShareAlike 4.0 International License. To view a copy of this license, visit http://creativecommons.org/licenses/by-sa/4.0/.",
      "custodian_organisation" : "openEHR Foundation",
      "original_namespace" : "org.openehr",
      "original_publisher" : "openEHR Foundation",
      "custodian_namespace" : "org.openehr",
      "MD5-CAM-1.0.1" : "68faa934834ec4744a82aab04bdd82df",
      "PARENT:MD5-CAM-1.0.1" : "8FE80F3E80C594AAF99D3BA540A53D73",
      "sem_ver" : "11.0.0",
      "build_uid" : ""
    },
    "details" : {
      "de" : {
        "@type" : "RESOURCE_DESCRIPTION_ITEM",
        "language" : {
          "terminologyId" : {
            "value" : "ISO_639-1"
          },
          "codeString" : "de"
        },
        "keywords" : [ ],
        "originalResourceUri" : { },
        "otherDetails" : { }
      },
      "ru" : {
        "@type" : "RESOURCE_DESCRIPTION_ITEM",
        "language" : {
          "terminologyId" : {
            "value" : "ISO_639-1"
          },
          "codeString" : "ru"
        },
        "keywords" : [ ],
        "originalResourceUri" : { },
        "otherDetails" : { }
      },
      "sv" : {
        "@type" : "RESOURCE_DESCRIPTION_ITEM",
        "language" : {
          "terminologyId" : {
            "value" : "ISO_639-1"
          },
          "codeString" : "sv"
        },
        "keywords" : [ ],
        "originalResourceUri" : { },
        "otherDetails" : { }
      },
      "es-ar" : {
        "@type" : "RESOURCE_DESCRIPTION_ITEM",
        "language" : {
          "terminologyId" : {
            "value" : "ISO_639-1"
          },
          "codeString" : "es-ar"
        },
        "keywords" : [ ],
        "originalResourceUri" : { },
        "otherDetails" : { }
      },
      "nb" : {
        "@type" : "RESOURCE_DESCRIPTION_ITEM",
        "language" : {
          "terminologyId" : {
            "value" : "ISO_639-1"
          },
          "codeString" : "nb"
        },
        "keywords" : [ ],
        "originalResourceUri" : { },
        "otherDetails" : { }
      },
      "pt-br" : {
        "@type" : "RESOURCE_DESCRIPTION_ITEM",
        "language" : {
          "terminologyId" : {
            "value" : "ISO_639-1"
          },
          "codeString" : "pt-br"
        },
        "keywords" : [ ],
        "originalResourceUri" : { },
        "otherDetails" : { }
      },
      "sl" : {
        "@type" : "RESOURCE_DESCRIPTION_ITEM",
        "language" : {
          "terminologyId" : {
            "value" : "ISO_639-1"
          },
          "codeString" : "sl"
        },
        "keywords" : [ ],
        "originalResourceUri" : { },
        "otherDetails" : { }
      },
      "en" : {
        "@type" : "RESOURCE_DESCRIPTION_ITEM",
        "language" : {
          "terminologyId" : {
            "value" : "ISO_639-1"
          },
          "codeString" : "en"
        },
        "keywords" : [ ],
        "originalResourceUri" : { },
        "otherDetails" : { }
      },
      "it" : {
        "@type" : "RESOURCE_DESCRIPTION_ITEM",
        "language" : {
          "terminologyId" : {
            "value" : "ISO_639-1"
          },
          "codeString" : "it"
        },
        "keywords" : [ ],
        "originalResourceUri" : { },
        "otherDetails" : { }
      },
      "fr" : {
        "@type" : "RESOURCE_DESCRIPTION_ITEM",
        "language" : {
          "terminologyId" : {
            "value" : "ISO_639-1"
          },
          "codeString" : "fr"
        },
        "keywords" : [ ],
        "originalResourceUri" : { },
        "otherDetails" : { }
      }
    }
  },
  "parentArchetypeId" : "openEHR-EHR-SECTION.adhoc.v1",
  "differential" : true,
  "archetypeId" : {
    "@type" : "ARCHETYPE_HRID",
    "value" : "openEHR-EHR-SECTION.clinicalprofile.v1"
  },
  "definition" : {
    "@type" : "C_COMPLEX_OBJECT",
    "rmTypeName" : "SECTION",
    "nodeId" : "at0000.1",
    "attributes" : [ {
      "@type" : "C_ATTRIBUTE",
      "rmAttributeName" : "items",
      "existence" : "0..1",
      "children" : [ {
        "@type" : "C_ARCHETYPE_ROOT",
        "rmTypeName" : "OBSERVATION",
        "occurrences" : "0..1",
        "nodeId" : "at0.71",
        "attributes" : [ ],
        "attributeTuples" : [ ],
        "archetypeRef" : "Symptom/sign screening - JM TB",
        "referenceType" : "templateId"
      }, {
        "@type" : "C_ARCHETYPE_ROOT",
        "rmTypeName" : "OBSERVATION",
        "occurrences" : "0..1",
        "nodeId" : "at0.48",
        "attributes" : [ ],
        "attributeTuples" : [ ],
        "archetypeRef" : "Problem/Diagnosis screening - JM TB",
        "referenceType" : "templateId"
      }, {
        "@type" : "C_ARCHETYPE_ROOT",
        "rmTypeName" : "OBSERVATION",
        "occurrences" : "0..1",
        "nodeId" : "at0.55",
        "attributes" : [ ],
        "attributeTuples" : [ ],
        "archetypeRef" : "Medication screening - JM TB",
        "referenceType" : "templateId"
      }, {
        "@type" : "C_ARCHETYPE_ROOT",
        "rmTypeName" : "OBSERVATION",
        "occurrences" : "0..1",
        "nodeId" : "at0.61",
        "attributes" : [ ],
        "attributeTuples" : [ ],
        "archetypeRef" : "Vaccination screening - JM TB",
        "referenceType" : "templateId"
      }, {
        "@type" : "C_ARCHETYPE_ROOT",
        "rmTypeName" : "OBSERVATION",
        "occurrences" : "0..1",
        "nodeId" : "at0.67",
        "attributes" : [ ],
        "attributeTuples" : [ ],
        "archetypeRef" : "Substance use screening - JM",
        "referenceType" : "templateId"
      }, {
        "@type" : "C_ARCHETYPE_ROOT",
        "rmTypeName" : "OBSERVATION",
        "occurrences" : "0..1",
        "nodeId" : "at0.27",
        "attributes" : [ ],
        "attributeTuples" : [ ],
        "archetypeRef" : "Pregnancy screening - JM",
        "referenceType" : "templateId"
      }, {
        "@type" : "C_ARCHETYPE_ROOT",
        "rmTypeName" : "EVALUATION",
        "occurrences" : "0..1",
        "nodeId" : "at0.69",
        "attributes" : [ ],
        "attributeTuples" : [ ],
        "archetypeRef" : "openEHR-EHR-EVALUATION.ovl-last_menstrual_period-001.v1",
        "referenceType" : "archetypeOverlay"
      } ]
    } ],
    "attributeTuples" : [ ]
  },
  "terminology" : {
    "@type" : "ARCHETYPE_TERMINOLOGY",
    "conceptCode" : "at0000",
    "termDefinitions" : {
      "en" : {
        "at0000.1" : {
          "@type" : "ARCHETYPE_TERM",
          "code" : "at0000.1",
          "text" : "Clinical profile - TB",
          "description" : "A generic section header which should be renamed in a template to suit a specific clinical context."
        }
      },
      "ru" : {
        "at0000.1" : {
          "@type" : "ARCHETYPE_TERM",
          "code" : "at0000.1",
          "text" : "Health status",
          "description" : "Образец заголовка раздела"
        }
      },
      "es-ar" : {
        "at0000.1" : {
          "@type" : "ARCHETYPE_TERM",
          "code" : "at0000.1",
          "text" : "Health status",
          "description" : "Un encabezado de sección de tipo genérico que será renombrado en una plantilla para su empleo en un contexto clínico específico."
        }
      },
      "sl" : {
        "at0000.1" : {
          "@type" : "ARCHETYPE_TERM",
          "code" : "at0000.1",
          "text" : "Health status",
          "description" : "Naslov sekcije"
        }
      },
      "nb" : {
        "at0000.1" : {
          "@type" : "ARCHETYPE_TERM",
          "code" : "at0000.1",
          "text" : "Health status",
          "description" : "En generisk seksjonsoverskrift som skal gis nytt navn i en templat for å passe i en gitt klinisk kontekst."
        }
      },
      "pt-br" : {
        "at0000.1" : {
          "@type" : "ARCHETYPE_TERM",
          "code" : "at0000.1",
          "text" : "Health status",
          "description" : "Um cabeçalho de sessão genérico que deve ser renomeado no template para adequar-se a um contexto clínico específico."
        }
      },
      "sv" : {
        "at0000.1" : {
          "@type" : "ARCHETYPE_TERM",
          "code" : "at0000.1",
          "text" : "Health status",
          "description" : "En allmän avsnittsrubrik som döps om i en openEHR-mall för att passa in i en specifik klinisk kontext."
        }
      },
      "de" : {
        "at0000.1" : {
          "@type" : "ARCHETYPE_TERM",
          "code" : "at0000.1",
          "text" : "Health status",
          "description" : "Eine generische Abschnittsüberschrift eines Templates, welche entsprechend dem spezifischen klinischen Kontext umbenannt werden sollte."
        }
      },
      "it" : {
        "at0000.1" : {
          "@type" : "ARCHETYPE_TERM",
          "code" : "at0000.1",
          "text" : "Health status",
          "description" : "Un'intestazione di sezione generica che dovrebbe essere rinominata in un template per adattarsi ad uno specifico contesto clinico."
        }
      },
      "fr" : {
        "at0000.1" : {
          "@type" : "ARCHETYPE_TERM",
          "code" : "at0000.1",
          "text" : "Health status",
          "description" : "Un en-tête de section générique qui doit être renommé dans un modèle pour s'adapter à un contexte clinique spécifique."
        }
      }
    },
    "termBindings" : { },
    "terminologyExtracts" : { },
    "valueSets" : { }
  },
  "adlVersion" : "1.4",
  "buildUid" : "fbd4b8d7-07e0-3c29-8508-6459c87b5906",
  "rmName" : "openehr",
  "rmRelease" : "1.1.0",
  "generated" : true,
  "templateId" : "Clinical profile - JM TB",
  "otherMetaData" : { },
  "templateOverlays" : [ {
    "@type" : "TEMPLATE_OVERLAY",
    "uid" : "4b26dad7-a7f3-4783-adfa-bfc428b29347",
    "description" : {
      "@type" : "RESOURCE_DESCRIPTION",
      "originalAuthor" : { },
      "otherContributors" : [ ],
      "ipAcknowledgements" : { },
      "references" : { },
      "conversionDetails" : { },
      "otherDetails" : {
        "PARENT:MD5-CAM-1.0.1" : "271CD0C30AF2A1828A0A2EA440800BBC"
      },
      "details" : {
        "nb" : {
          "@type" : "RESOURCE_DESCRIPTION_ITEM",
          "language" : {
            "terminologyId" : {
              "value" : "ISO_639-1"
            },
            "codeString" : "nb"
          },
          "purpose" : "For å registrere detaljer om den første dagen i den siste menstruasjonsperioden individet opplevde.",
          "keywords" : [ "menstruasjon, mensen, LNMP, LMP, LNP, DLMP" ],
          "use" : "Brukes for å registrere detaljer om den første dagen i den siste menstruasjonsperioden individet opplevde.\r\n\r\nBruk dataelementet \"Sikkerhet\" for å registrere sikkerhetsgraden for at datoen var korrekt. Ved registrering av startdatoen for siste menstruasjonsperiode er antagelsen at denne menstruasjonen var normal.",
          "misuse" : "Brukes ikke for å registrere detaljer om menarke eller overgangsalder - bruk arketypen EVALUATION.menstruation_summary for dette formålet.\r\n\r\nBrukes ikke for å registrere informasjon om en spesifikk dag i menstruasjonssyklusen, bruk arketypen OBSERVATION.menstrual_diary for dette formålet.\r\n\r\nBrukes ikke for å registrere informasjon om typiske eller vanlige menstruasjonssykluser eller mønstre - bruk arketypen EVALUATION.menstruation_summary for dette formålet.",
          "copyright" : "© openEHR Foundation",
          "originalResourceUri" : { },
          "otherDetails" : { }
        },
        "en" : {
          "@type" : "RESOURCE_DESCRIPTION_ITEM",
          "language" : {
            "terminologyId" : {
              "value" : "ISO_639-1"
            },
            "codeString" : "en"
          },
          "purpose" : "To record the details about the first day of the most recent menstrual cycle for the individual.",
          "keywords" : [ "menstruation, menses, LNMP, LMP, LNP, DLMP" ],
          "use" : "Use to record the details about the first day of the most recent menstrual cycle for the individual. \r\n\r\nUse the data element 'Certainty' to record the level of certainty the date was correct. The assumption when recording the onset of the last menstrual cycle is that the menstruation was 'normal'.",
          "misuse" : "Not to be used to record information about menses or related symptoms, use the OBSERVATION.menstruation archetype for this purpose. \r\n\r\nNot to be used to record information about a specific day in a menstrual cycle, use the OBSERVATION.menstrual_diary archetype for this purpose.\r\n\r\nNot to be used to record information about an individual's menstruation history events or patterns of menstruation over time, use the EVALUATION.menstruation_summary archetype for this purpose.",
          "copyright" : "© openEHR Foundation",
          "originalResourceUri" : { },
          "otherDetails" : { }
        }
      }
    },
    "parentArchetypeId" : "openEHR-EHR-EVALUATION.last_menstrual_period.v1",
    "differential" : true,
    "archetypeId" : {
      "@type" : "ARCHETYPE_HRID",
      "value" : "openEHR-EHR-EVALUATION.ovl-last_menstrual_period-001.v1"
    },
    "definition" : {
      "@type" : "C_COMPLEX_OBJECT",
      "rmTypeName" : "EVALUATION",
      "nodeId" : "at0000.1",
      "attributes" : [ {
        "@type" : "C_ATTRIBUTE",
        "rmAttributeName" : "data",
        "children" : [ {
          "@type" : "C_COMPLEX_OBJECT",
          "rmTypeName" : "ITEM_TREE",
          "nodeId" : "at0001",
          "attributes" : [ {
            "@type" : "C_ATTRIBUTE",
            "rmAttributeName" : "items",
            "children" : [ {
              "@type" : "C_COMPLEX_OBJECT",
              "rmTypeName" : "ELEMENT",
              "occurrences" : "0..0",
              "nodeId" : "at0009.1",
              "attributes" : [ {
                "@type" : "C_ATTRIBUTE",
                "rmAttributeName" : "value",
                "children" : [ {
                  "@type" : "C_COMPLEX_OBJECT",
                  "rmTypeName" : "DV_TEXT",
                  "attributes" : [ ],
                  "attributeTuples" : [ ]
                }, {
                  "@type" : "C_COMPLEX_OBJECT",
                  "rmTypeName" : "DV_CODED_TEXT",
                  "attributes" : [ ],
                  "attributeTuples" : [ ]
                } ]
              } ],
              "attributeTuples" : [ ]
            }, {
              "@type" : "C_COMPLEX_OBJECT",
              "rmTypeName" : "ELEMENT",
              "occurrences" : "0..0",
              "nodeId" : "at0007.1",
              "attributes" : [ ],
              "attributeTuples" : [ ]
            }, {
              "@type" : "C_COMPLEX_OBJECT",
              "rmTypeName" : "ELEMENT",
              "occurrences" : "0..0",
              "nodeId" : "at0008.1",
              "attributes" : [ ],
              "attributeTuples" : [ ]
            } ]
          } ],
          "attributeTuples" : [ ]
        } ]
      }, {
        "@type" : "C_ATTRIBUTE",
        "rmAttributeName" : "protocol",
        "children" : [ {
          "@type" : "C_COMPLEX_OBJECT",
          "rmTypeName" : "ITEM_TREE",
          "nodeId" : "at0003",
          "attributes" : [ {
            "@type" : "C_ATTRIBUTE",
            "rmAttributeName" : "items",
            "children" : [ {
              "@type" : "C_COMPLEX_OBJECT",
              "rmTypeName" : "ELEMENT",
              "occurrences" : "0..0",
              "nodeId" : "at0004.1",
              "attributes" : [ ],
              "attributeTuples" : [ ]
            } ]
          } ],
          "attributeTuples" : [ ]
        } ]
      } ],
      "attributeTuples" : [ ]
    },
    "terminology" : {
      "@type" : "ARCHETYPE_TERMINOLOGY",
      "conceptCode" : "at0000",
      "termDefinitions" : {
        "en" : { },
        "nb" : { }
      },
      "termBindings" : { },
      "terminologyExtracts" : { },
      "valueSets" : { }
    },
    "adlVersion" : "1.4",
    "buildUid" : "ae09ea7b-787c-494c-a987-89845ef29295",
    "rmName" : "openehr",
    "rmRelease" : "1.1.0",
    "generated" : true,
    "otherMetaData" : { },
    "originalLanguage" : {
      "terminologyId" : {
        "value" : "ISO_639-1"
      },
      "codeString" : "en"
    },
    "translations" : [ {
      "@type" : "TRANSLATION_DETAILS",
      "language" : {
        "terminologyId" : {
          "value" : "ISO_639-1"
        },
        "codeString" : "nb"
      },
      "author" : {
        "name" : "Marit Alice Venheim, John Tore Valand",
        "organisation" : "Helse Vest IKT",
        "email" : "marit.alice.venheim@helse-vest-ikt.no, john.tore.valand@helse-vest-ikt.no"
      },
      "otherDetails" : { }
    } ]
  } ],
  "originalLanguage" : {
    "terminologyId" : {
      "value" : "ISO_639-1"
    },
    "codeString" : "en"
  },
  "translations" : [ {
    "@type" : "TRANSLATION_DETAILS",
    "language" : {
      "terminologyId" : {
        "value" : "ISO_639-1"
      },
      "codeString" : "de"
    },
    "author" : { },
    "otherDetails" : { }
  }, {
    "@type" : "TRANSLATION_DETAILS",
    "language" : {
      "terminologyId" : {
        "value" : "ISO_639-1"
      },
      "codeString" : "ru"
    },
    "author" : { },
    "otherDetails" : { }
  }, {
    "@type" : "TRANSLATION_DETAILS",
    "language" : {
      "terminologyId" : {
        "value" : "ISO_639-1"
      },
      "codeString" : "sv"
    },
    "author" : { },
    "otherDetails" : { }
  }, {
    "@type" : "TRANSLATION_DETAILS",
    "language" : {
      "terminologyId" : {
        "value" : "ISO_639-1"
      },
      "codeString" : "es-ar"
    },
    "author" : { },
    "otherDetails" : { }
  }, {
    "@type" : "TRANSLATION_DETAILS",
    "language" : {
      "terminologyId" : {
        "value" : "ISO_639-1"
      },
      "codeString" : "nb"
    },
    "author" : { },
    "otherDetails" : { }
  }, {
    "@type" : "TRANSLATION_DETAILS",
    "language" : {
      "terminologyId" : {
        "value" : "ISO_639-1"
      },
      "codeString" : "pt-br"
    },
    "author" : { },
    "otherDetails" : { }
  }, {
    "@type" : "TRANSLATION_DETAILS",
    "language" : {
      "terminologyId" : {
        "value" : "ISO_639-1"
      },
      "codeString" : "sl"
    },
    "author" : { },
    "otherDetails" : { }
  }, {
    "@type" : "TRANSLATION_DETAILS",
    "language" : {
      "terminologyId" : {
        "value" : "ISO_639-1"
      },
      "codeString" : "it"
    },
    "author" : { },
    "otherDetails" : { }
  }, {
    "@type" : "TRANSLATION_DETAILS",
    "language" : {
      "terminologyId" : {
        "value" : "ISO_639-1"
      },
      "codeString" : "fr"
    },
    "author" : { },
    "otherDetails" : { }
  } ]
}